LICENSE.txt
MANIFEST.in
README.rst
setup.cfg
setup.py
cpbd/__init__.py
cpbd/compute.py
cpbd/octave.py
cpbd.egg-info/PKG-INFO
cpbd.egg-info/SOURCES.txt
cpbd.egg-info/dependency_links.txt
cpbd.egg-info/requires.txt
cpbd.egg-info/top_level.txt