Metadata-Version: 1.1
Name: cpbd
Version: 1.0.7
Summary: Calculate the sharpness of an image with the CPBD metric
Home-page: https://github.com/0x64746b/python-cpbd
Author: D.
Author-email: dtk@gmx.de
License: Other/Proprietary License
Keywords: sharpness,metric,blur,cumulative probability,no-reference,objective,perceptual
Platform: UNKNOWN
Classifier: Development Status :: 5 - Production/Stable
Classifier: Intended Audience :: Science/Research
Classifier: Topic :: Scientific/Engineering
Classifier: License :: Other/Proprietary License
Classifier: Programming Language :: Python :: 2.7
Classifier: Programming Language :: Python :: 3.5
Classifier: Programming Language :: Python :: 3.6
